[
  {
    "id": 10,
    "name": "Найкрашэ",
    "description": "Завжди",
    "price": 211111.0,
    "category_id": 4,
    "photo_url": "https://api.telegram.org/file/bot8295835490:AAHFv9nWMVXl6PWgQqUWSf7Nj1SCzxEURZc/photos/file_21.jpg"
  },
  {
    "id": 9,
    "name": "Е Е Е Е",
    "description": "е",
    "price": 777.0,
    "category_id": 2,
    "photo_url": "https://api.telegram.org/file/bot8295835490:AAHFv9nWMVXl6PWgQqUWSf7Nj1SCzxEURZc/photos/file_22"
  },
  {
    "id": 8,
    "name": "йсцкйцкс",
    "description": "уннуиун",
    "price": 616.0,
    "category_id": 2,
    "photo_url": "https://api.telegram.org/file/bot8295835490:AAHFv9nWMVXl6PWgQqUWSf7Nj1SCzxEURZc/photos/file_23"
  },
  {
    "id": 7,
    "name": "спочатку",
    "description": "вид",
    "price": 12.0,
    "category_id": 2,
    "photo_url": null
  },
  {
    "id": 6,
    "name": "Сперматозойд собачий",
    "description": "цкмйцмкйц",
    "price": 61.0,
    "category_id": 2,
    "photo_url": "https://api.telegram.org/file/bot8295835490:AAHFv9nWMVXl6PWgQqUWSf7Nj1SCzxEURZc/photos/file_24"
  },
  {
    "id": 5,
    "name": "crqrqw",
    "description": "teqbt",
    "price": 5613.0,
    "category_id": 2,
    "photo_url": null
  },
  {
    "id": 4,
    "name": "cqwrq",
    "description": "cwr",
    "price": 51515.0,
    "category_id": 2,
    "photo_url": null
  },
  {
    "id": 3,
    "name": "йцккмйцк",
    "description": "йцмкйцкмй",
    "price": 31241.0,
    "category_id": 2,
    "photo_url": "https://api.telegram.org/file/bot8295835490:AAHFv9nWMVXl6PWgQqUWSf7Nj1SCzxEURZc/photos/file_25"
  },
  {
    "id": 2,
    "name": "ПИДОРАС",
    "description": "ЙЦСКЙЦКС",
    "price": 4141515.0,
    "category_id": 2,
    "photo_url": "https://api.telegram.org/file/bot8295835490:AAHFv9nWMVXl6PWgQqUWSf7Nj1SCzxEURZc/photos/file_26"
  },
  {
    "id": 1,
    "name": "Шлюха",
    "description": "Дешевая блядота",
    "price": 2141.0,
    "category_id": 2,
    "photo_url": "https://api.telegram.org/file/bot8295835490:AAHFv9nWMVXl6PWgQqUWSf7Nj1SCzxEURZc/photos/file_27"
  }
]